LICENSE
MANIFEST.in
README.md
setup.cfg
notifier/__init__.py
notifier/main.py
notifier/resources/config.json
notifier_altear-0.0.2.dist-info/METADATA
notifier_altear-0.0.2.dist-info/RECORD
notifier_altear-0.0.2.dist-info/WHEEL
notifier_altear-0.0.2.dist-info/entry_points.txt
notifier_altear-0.0.2.dist-info/top_level.txt
notifier_altear.egg-info/PKG-INFO
notifier_altear.egg-info/SOURCES.txt
notifier_altear.egg-info/dependency_links.txt
notifier_altear.egg-info/entry_points.txt
notifier_altear.egg-info/requires.txt
notifier_altear.egg-info/top_level.txt
