Metadata-Version: 2.1
Name: notifier-altear
Version: 0.0.2
Summary: A small package for sending notification emails
Home-page: UNKNOWN
Author: Andre Telfer
Author-email: andretelfer@gmail.com
License: UNKNOWN
Platform: UNKNOWN
Classifier: Programming Language :: Python :: 3
Classifier: License :: OSI Approved :: MIT License
Classifier: Operating System :: OS Independent
Requires-Dist: click
